MANIFEST.in
requirements.txt
run_musicazoo.sh
settings.json
setup.cfg
setup.py
supervisord.conf
bin/musicazoo
bin/mz
bin/mz_push_email
bin/mz_push_fortune
musicazoo/__init__.py
musicazoo/cli.py
musicazoo/queue.py
musicazoo.egg-info/PKG-INFO
musicazoo.egg-info/SOURCES.txt
musicazoo.egg-info/dependency_links.txt
musicazoo.egg-info/not-zip-safe
musicazoo.egg-info/requires.txt
musicazoo.egg-info/top_level.txt
musicazoo/../requirements.txt
musicazoo/../settings.json
musicazoo/../supervisord.conf
musicazoo/../static/de.html
musicazoo/../static/front.html
musicazoo/../static/index.html
musicazoo/../static/mirror.html
musicazoo/../static/mztop.html
musicazoo/../static/settings.json
musicazoo/../static/assets/DINPro-Black.otf
musicazoo/../static/assets/DINPro-Bold.otf
musicazoo/../static/assets/DINPro-Light.otf
musicazoo/../static/assets/DINPro-Medium.otf
musicazoo/../static/assets/DINPro-Regular.otf
musicazoo/../static/assets/backbone.js
musicazoo/../static/assets/handlebars.js
musicazoo/../static/assets/jquery-ui.js
musicazoo/../static/assets/jquery.min.js
musicazoo/../static/assets/jquery.ui.touch-punch.min.js
musicazoo/../static/assets/json2.js
musicazoo/../static/assets/mz-de.css
musicazoo/../static/assets/mz-new.css
musicazoo/../static/assets/mz_bb.js
musicazoo/../static/assets/mz_mirror.js
musicazoo/../static/assets/shmooze.js
musicazoo/../static/assets/underscore.js
musicazoo/../static/assets/underscore.string.min.js
musicazoo/../static/assets/images/ctrl-10r.png
musicazoo/../static/assets/images/ctrl-next.png
musicazoo/../static/assets/images/ctrl-pause.png
musicazoo/../static/assets/images/ctrl-play.png
musicazoo/../static/assets/images/ctrl-rr.png
musicazoo/../static/assets/images/mz.png
musicazoo/../static/assets/images/rm.png
musicazoo/../static/assets/images/speed-15x.png
musicazoo/../static/assets/images/speed-1x.png
musicazoo/../static/assets/images/speed-2x.png
musicazoo/../static/assets/images/vol-empty.png
musicazoo/../static/assets/images/vol-full.png
musicazoo/../static/assets/images/vol-icon-mute.png
musicazoo/../static/assets/images/vol-icon.png
musicazoo/../static/assets/images/vol.psd
musicazoo/lib/__init__.py
musicazoo/lib/graphics.py
