Metadata-Version: 1.1
Name: musicazoo
Version: 5.2.6
Summary: Modular media player
Home-page: https://github.com/zbanks/musicazoo
Author: Zach Banks
Author-email: zbanks@mit.edu
License: UNKNOWN
Download-URL: https://github.com/zbanks/musicazoo/tarball/5.2.6
Platform: UNKNOWN
